COVID19analysis/COVID19analysis.py
COVID19analysis/__init__.py
COVID19analysis-1.2.7.dist-info/LICENSE
COVID19analysis-1.2.7.dist-info/METADATA
COVID19analysis-1.2.7.dist-info/WHEEL
COVID19analysis-1.2.7.dist-info/top_level.txt
COVID19analysis-1.2.7.dist-info/RECORD
