Metadata-Version: 2.1
Name: COVID19analysis
Version: 1.2.7
Summary: COVID19Analysis based on CSSEGISandData on GitHub
Home-page: https://github.com/prasannaba/COVID-19_Analysis_Library
Author: Prasanna
Author-email: prasanna.badami@hotmail.com
License: MIT
Platform: UNKNOWN
Classifier: Development Status :: 5 - Production/Stable
Classifier: License :: OSI Approved :: MIT License
Classifier: Programming Language :: Python
Classifier: Programming Language :: Python :: 3.7
Classifier: Programming Language :: Python :: 3.8
Classifier: Topic :: Scientific/Engineering
Classifier: Topic :: Scientific/Engineering :: Mathematics
Classifier: Topic :: Scientific/Engineering :: Visualization
Classifier: Topic :: Software Development :: Libraries
Classifier: Topic :: Software Development :: Libraries :: Python Modules
Classifier: Intended Audience :: Developers
Classifier: Intended Audience :: Science/Research
Classifier: Intended Audience :: Information Technology
Classifier: Intended Audience :: Financial and Insurance Industry
Requires-Python: >=3.7
License-File: LICENSE
Requires-Dist: bokeh (>=2.3.3)
Requires-Dist: panel (>=0.11.3)
Requires-Dist: pandas (>=1.3.5)
Requires-Dist: holoviews (>=1.14.4)
Requires-Dist: hvplot (>=0.7.2)
Requires-Dist: tqdm (>=4.61.2)
